sage_contact/__init__.py
sage_contact/admin/__init__.py
sage_contact/admin/support.py
sage_contact/api/__init__.py
sage_contact/apps.py
sage_contact/constants/__init__.py
sage_contact/constants/choices.py
sage_contact/constants/settings.py
sage_contact/forms/__init__.py
sage_contact/forms/mixins/__init__.py
sage_contact/forms/mixins/geo_ip.py
sage_contact/forms/support.py
sage_contact/migrations/__init__.py
sage_contact/models/__init__.py
sage_contact/models/contact.py
sage_contact/models/helper/__init__.py
sage_contact/models/helper/enums/__init__.py
sage_contact/models/mixins/__init__.py
sage_contact/models/support.py
sage_contact/repository/__init__.py
sage_contact/repository/manager/__init__.py
sage_contact/repository/manager/contact.py
sage_contact/repository/queryset/__init__.py
sage_contact/repository/queryset/contact.py
sage_contact/settings/__init__.py
sage_contact/settings/check.py
sage_contact/settings/exc.py
sage_contact/settings/helper/__init__.py
sage_contact/signals/__init__.py
sage_contact/signals/support.py
sage_contact/tests/__init__.py
sage_contact/utils/__init__.py
sage_contact/validators/__init__.py
sage_contact/views/__init__.py
sage_contact/views/support.py
django_sage_contact-0.1.2.dist-info/LICENSE
django_sage_contact-0.1.2.dist-info/METADATA
django_sage_contact-0.1.2.dist-info/WHEEL
django_sage_contact-0.1.2.dist-info/RECORD
