Metadata-Version: 2.1
Name: django-sage-contact
Version: 0.1.2
Summary: Django package to handle user contact information and contact form.
License: MIT
Author: Sepehr Akbarzadeh
Author-email: sa.goldeneagle@gmail.com
Requires-Python: >=3.8,<4.0
Classifier: License :: OSI Approved :: MIT License
Classifier: Programming Language :: Python :: 3
Classifier: Programming Language :: Python :: 3.8
Classifier: Programming Language :: Python :: 3.9
Classifier: Programming Language :: Python :: 3.10
Classifier: Programming Language :: Python :: 3.11
Classifier: Programming Language :: Python :: 3.12
Requires-Dist: django (>=4.2,<6.0)
Requires-Dist: django-countries (>=7.6.1,<8.0.0)
Requires-Dist: django-phonenumber-field[phonenumbers] (>=8.0.0,<9.0.0)
Requires-Dist: django-polymorphic (>=3.1.0,<4.0.0)
Requires-Dist: geoip2 (>=4.8.0,<5.0.0)
